fundamentus/__init__.py
fundamentus_py-0.0.1.dist-info/LICENSE
fundamentus_py-0.0.1.dist-info/METADATA
fundamentus_py-0.0.1.dist-info/WHEEL
fundamentus_py-0.0.1.dist-info/top_level.txt
fundamentus_py-0.0.1.dist-info/RECORD
