Metadata-Version: 2.1
Name: fundamentus-py
Version: 0.0.1
Summary: Scrap data from Fundamentus.
Home-page: UNKNOWN
Author: Nikolas Silva
Author-email: <nikolas.rsilva@gmail.com>
License: UNKNOWN
Keywords: python,fundamentus
Platform: UNKNOWN
Classifier: Development Status :: 1 - Planning
Classifier: Intended Audience :: Developers
Classifier: Programming Language :: Python :: 3
Classifier: Operating System :: Unix
Classifier: Operating System :: MacOS :: MacOS X
Classifier: Operating System :: Microsoft :: Windows
